optimizationalgo
