Metadata-Version: 2.1
Name: optimizationalgo
Version: 0.0.10
Summary: Optimization algorithms for the traveling salesman problem
Home-page: https://github.com/SMALA-comand/Optimization_algo
Author: Mark Kozlov
Author-email: mark.k.2012@yandex.ru
License: UNKNOWN
Platform: UNKNOWN
Classifier: Programming Language :: Python :: 3.9
Classifier: License :: OSI Approved :: MIT License
Classifier: Operating System :: OS Independent
